cyclic_boosting/GBSregression.py
cyclic_boosting/__init__.py
cyclic_boosting/base.py
cyclic_boosting/binning/__init__.py
cyclic_boosting/binning/_binary_search.py
cyclic_boosting/binning/_utils.py
cyclic_boosting/binning/bin_number_transformer.py
cyclic_boosting/binning/ecdf_transformer.py
cyclic_boosting/classification.py
cyclic_boosting/common_smoothers.py
cyclic_boosting/features.py
cyclic_boosting/flags.py
cyclic_boosting/generic_loss.py
cyclic_boosting/interaction_selection.py
cyclic_boosting/learning_rate.py
cyclic_boosting/link.py
cyclic_boosting/location.py
cyclic_boosting/nbinom.py
cyclic_boosting/observers.py
cyclic_boosting/pipelines.py
cyclic_boosting/plots/_1dplots.py
cyclic_boosting/plots/_2dplots.py
cyclic_boosting/plots/__init__.py
cyclic_boosting/plots/plot_utils.py
cyclic_boosting/price.py
cyclic_boosting/quantile_matching.py
cyclic_boosting/regression.py
cyclic_boosting/smoothing/__init__.py
cyclic_boosting/smoothing/base.py
cyclic_boosting/smoothing/extrapolate.py
cyclic_boosting/smoothing/meta_smoother.py
cyclic_boosting/smoothing/multidim.py
cyclic_boosting/smoothing/onedim.py
cyclic_boosting/smoothing/orthofit.py
cyclic_boosting/utils.py
cyclic_boosting-1.4.0.dist-info/LICENSE
cyclic_boosting-1.4.0.dist-info/METADATA
cyclic_boosting-1.4.0.dist-info/WHEEL
cyclic_boosting-1.4.0.dist-info/RECORD
