Metadata-Version: 2.1
Name: cyclic-boosting
Version: 1.4.0
Summary: Implementation of Cyclic Boosting machine learning algorithms
Author: Blue Yonder GmbH
Requires-Python: >=3.8,<3.12
Classifier: License :: OSI Approved :: Eclipse Public License 2.0 (EPL-2.0)
Classifier: Programming Language :: Python
Classifier: Programming Language :: Python :: 3
Classifier: Programming Language :: Python :: 3.8
Classifier: Programming Language :: Python :: 3.9
Classifier: Programming Language :: Python :: 3.10
Classifier: Programming Language :: Python :: 3.11
Classifier: Programming Language :: Python :: 3 :: Only
Classifier: Topic :: Scientific/Engineering :: Artificial Intelligence
Requires-Dist: decorator (>=5.1.1)
Requires-Dist: hypothesis (>=6.70.0)
Requires-Dist: matplotlib (>=1.5.1)
Requires-Dist: numba (>=0.56.4)
Requires-Dist: numexpr (>=2.5.2)
Requires-Dist: numpy (>=1.12.1)
Requires-Dist: pandas (>=0.20.3)
Requires-Dist: scikit-learn (>=0.18.2)
Requires-Dist: scipy (>=1.10)
Requires-Dist: six (>=1.16.0)
